pyws1uem/__init__.py
pyws1uem/client.py
pyws1uem/error.py
pyws1uem/mam/__init__.py
pyws1uem/mam/mam.py
pyws1uem/mdm/__init__.py
pyws1uem/mdm/devices.py
pyws1uem/mdm/mdm.py
pyws1uem/mdm/tags.py
pyws1uem/mem/__init__.py
pyws1uem/mem/mem.py
pyws1uem/system/__init__.py
pyws1uem/system/groups.py
pyws1uem/system/info.py
pyws1uem/system/system.py
pyws1uem/system/users.py
pyws1uem-0.0.10.dist-info/LICENSE
pyws1uem-0.0.10.dist-info/METADATA
pyws1uem-0.0.10.dist-info/WHEEL
pyws1uem-0.0.10.dist-info/top_level.txt
pyws1uem-0.0.10.dist-info/RECORD
