Metadata-Version: 2.1
Name: pyws1uem
Version: 0.0.10
Summary: PyWorkspaceOneUEM is a Python API library for VMware Workspace ONE UEM formerly known as AirWatch
Home-page: https://github.com/marcofuchs89/PyWorkspaceOne
Author: marcofuchs89
Author-email: marco@fusche.net
License: MIT
Keywords: uem airwatch api
Platform: UNKNOWN
Classifier: Development Status :: 3 - Alpha
Classifier: Intended Audience :: Developers
Classifier: Topic :: Software Development :: Libraries
Classifier: Programming Language :: Python :: 3.9
Classifier: License :: OSI Approved :: MIT License
Classifier: Operating System :: OS Independent
Requires-Python: >=3.9
License-File: LICENSE
Requires-Dist: requests
